miskibin/__init__.py
miskibin/_logging_utils.py
miskibin/utils.py
miskibin-1.2.4.dist-info/METADATA
miskibin-1.2.4.dist-info/WHEEL
miskibin-1.2.4.dist-info/top_level.txt
miskibin-1.2.4.dist-info/RECORD
