Metadata-Version: 2.1
Name: miskibin
Version: 1.2.4
Summary: My personal package for colored logs. Highly customizable.
Home-page: https://github.com/michalskibinski109/miskibin
Author: Michał Skibiński
Author-email: mskibinski109@gmail.com
Classifier: Programming Language :: Python :: 3
Classifier: License :: OSI Approved :: MIT License
Classifier: Operating System :: OS Independent
Requires-Python: >=3.8
